README.txt
setup.py
mytestlib/__init__.py
mytestlib/greet.py
mytestlib_AkioTest.egg-info/PKG-INFO
mytestlib_AkioTest.egg-info/SOURCES.txt
mytestlib_AkioTest.egg-info/dependency_links.txt
mytestlib_AkioTest.egg-info/top_level.txt