Metadata-Version: 1.0
Name: mytestlib-AkioTest
Version: 1.0.0
Summary: My Test Library.
Home-page: http://dummy.org
Author: Akio Shuto
Author-email: syuto@vir.bekkoame.ne.jp
License: UNKNOWN
Platform: UNKNOWN
